untable.py
untable-0.1.dist-info/LICENSE
untable-0.1.dist-info/METADATA
untable-0.1.dist-info/WHEEL
untable-0.1.dist-info/top_level.txt
untable-0.1.dist-info/RECORD
