Metadata-Version: 2.1
Name: untable
Version: 0.1
Project-URL: Source, https://github.com/ubalklen/untable
License-File: LICENSE
Requires-Dist: beautifulsoup4
